PyraUtils/__init__.py
PyraUtils/cli.py
PyraUtils/common/__init__.py
PyraUtils/common/_cerberus.py
PyraUtils/common/_file.py
PyraUtils/common/_json.py
PyraUtils/common/_shelve.py
PyraUtils/common/_strings.py
PyraUtils/common/_time.py
PyraUtils/common/cert.py
PyraUtils/common/download.py
PyraUtils/common/rsync.py
PyraUtils/db/__init__.py
PyraUtils/db/_sqlalchemy.py
PyraUtils/db/_sqlite3.py
PyraUtils/http/__init__.py
PyraUtils/http/_httpx.py
PyraUtils/http/_jwt.py
PyraUtils/http/_oauth2.py
PyraUtils/http/_request.py
PyraUtils/log/__init__.py
PyraUtils/log/logger/__init__.py
PyraUtils/log/logger/_logging.py
PyraUtils/log/logger/_loguru.py
PyraUtils/network/__init__.py
PyraUtils/network/_ipaddress.py
PyraUtils/network/_mac.py
PyraUtils/network/_ssl.py
PyraUtils/password/__init__.py
PyraUtils/password/_password.py
PyraUtils/password/password_hash_tester.py
PyraUtils/service/__init__.py
PyraUtils/service/work_wechat/AbstractApi.py
PyraUtils/service/work_wechat/CorpApi.py
PyraUtils/service/work_wechat/CorpApiType.py
PyraUtils/service/work_wechat/WXBizMsgCrypt3.py
PyraUtils/service/work_wechat/__init__.py
PyraUtils/signature/__init__.py
PyraUtils/signature/_hashlib.py
PyraUtils/signature/_hmac.py
PyraUtils/signature/_signature.py
PyraUtils-0.9.35.dist-info/AUTHORS.rst
PyraUtils-0.9.35.dist-info/LICENSE
PyraUtils-0.9.35.dist-info/METADATA
PyraUtils-0.9.35.dist-info/WHEEL
PyraUtils-0.9.35.dist-info/top_level.txt
PyraUtils-0.9.35.dist-info/RECORD
